sdbtool/__init__.py
sdbtool/__main__.py
sdbtool/attributes.py
sdbtool/gui.py
sdbtool/info.py
sdbtool/sdb2xml.py
sdbtool/xml.py
sdbtool/apphelp/__init__.py
sdbtool/apphelp/winapi.py
sdbtool/apphelp/tags/Win10.py
sdbtool/apphelp/tags/__init__.py
sdbtool/cli/__init__.py
sdbtool/cli/attributes.py
sdbtool/cli/gui.py
sdbtool/cli/info.py
sdbtool/cli/sdb2xml.py
sdbtool/cli/types.py
sdbtool-0.7.2.dist-info/METADATA
sdbtool-0.7.2.dist-info/WHEEL
sdbtool-0.7.2.dist-info/entry_points.txt
sdbtool-0.7.2.dist-info/licenses/LICENSE.txt
sdbtool-0.7.2.dist-info/RECORD
