Metadata-Version: 2.4
Name: sdbtool
Version: 0.7.2
Summary: Interact with .sdb files using apphelp.dll
Project-URL: Homepage, https://pypi.org/project/sdbtool/
Project-URL: Changelog, https://github.com/learn-more/sdbtool/releases
Project-URL: Issues, https://github.com/learn-more/sdbtool/issues
Project-URL: CI, https://github.com/learn-more/sdbtool/actions
Project-URL: Repository, https://github.com/learn-more/sdbtool
Author-email: Mark Jansen <mark.jansen@reactos.org>
License-Expression: MIT
License-File: LICENSE.txt
Keywords: appcompat,apphelp,sdb,sdb2xml,sdbtool,shim,shimeng
Classifier: Development Status :: 4 - Beta
Classifier: Environment :: Console
Classifier: Operating System :: Microsoft :: Windows
Classifier: Programming Language :: Python :: 3
Classifier: Programming Language :: Python :: 3.10
Classifier: Programming Language :: Python :: 3.11
Classifier: Programming Language :: Python :: 3.12
Classifier: Programming Language :: Python :: 3.13
Classifier: Topic :: Utilities
Requires-Python: >=3.10
Requires-Dist: click>=8.2.1
